pythingy/__init__.py
pythingy/battery.py
pythingy/delegate.py
pythingy/environment.py
pythingy/motion.py
pythingy/sound.py
pythingy/static.py
pythingy/ui.py
pythingy/uuid.py
pythingy-0.1.dist-info/LICENSE
pythingy-0.1.dist-info/METADATA
pythingy-0.1.dist-info/WHEEL
pythingy-0.1.dist-info/top_level.txt
pythingy-0.1.dist-info/RECORD
