Metadata-Version: 2.1
Name: pythingy
Version: 0.1
Summary: Nordic Thingy52 Interface Module
Home-page: https://github.com/chevalierdebalibari/pythingy
Author: Nebojsa Stojiljkovic
Author-email: nebojsa@keemail.me
License: MIT
Platform: UNKNOWN
